reretry/__init__.py
reretry/api.py
reretry/compat.py
reretry-0.11.7.dist-info/AUTHORS
reretry-0.11.7.dist-info/LICENSE
reretry-0.11.7.dist-info/METADATA
reretry-0.11.7.dist-info/WHEEL
reretry-0.11.7.dist-info/pbr.json
reretry-0.11.7.dist-info/top_level.txt
reretry-0.11.7.dist-info/RECORD
